scicomb/__init__.py
scicomb-0.0.0.dist-info/licenses/LICENSE
scicomb-0.0.0.dist-info/METADATA
scicomb-0.0.0.dist-info/WHEEL
scicomb-0.0.0.dist-info/top_level.txt
scicomb-0.0.0.dist-info/RECORD
