Metadata-Version: 2.4
Name: scicomb
Version: 0.0.0
Summary: The Upstream Data ETL Engine of the V.I.N.E. Initiative
Author-email: SJRnhqh <sjrnhqh@outlook.com>
License: Apache-2.0
Requires-Python: >=3.13
License-File: LICENSE
Dynamic: license-file
